<core:FragmentDefinition
    xmlns="sap.m"
    xmlns:core="sap.ui.core"
    xmlns:l="sap.ui.layout"
    xmlns:f="sap.ui.layout.form"
>
            <Panel headerText="Header Text" expanded="true" expandable="true" >
                <headerToolbar>
                    <Toolbar>
                        <content>
                            <Title text="Condition"></Title>
                            <ToolbarSpacer ></ToolbarSpacer>
                            <Button text="Search" icon="sap-icon://search" press="onSearch"></Button>
                        </content>
                    </Toolbar>
                </headerToolbar>
                    <content>
                    <FlexBox>
                        <Label text="Student No"></Label>
                        <Input description="Input Student Number"/>
                    </FlexBox>
                    </content>
            </Panel>
</core:FragmentDefinition>